spacerescue/__init__.py
spacerescue/__main__.py
spacerescue/constants.py
spacerescue/core/math.py
spacerescue/core/pyray.py
spacerescue/core/types.py
spacerescue/gameplay/cameras/camera_entity.py
spacerescue/gameplay/cameras/camera_follower.py
spacerescue/gameplay/cameras/camera_galaxy.py
spacerescue/gameplay/cameras/camera_simulator.py
spacerescue/gameplay/challenges/challenge1.py
spacerescue/gameplay/challenges/challenge2.py
spacerescue/gameplay/challenges/challenge3.py
spacerescue/gameplay/databases/database.py
spacerescue/gameplay/effects/parallax.py
spacerescue/gameplay/effects/star_field.py
spacerescue/gameplay/physic/galaxy/asteroid.py
spacerescue/gameplay/physic/galaxy/dust.py
spacerescue/gameplay/physic/galaxy/galaxy.py
spacerescue/gameplay/physic/galaxy/galaxy_generator.py
spacerescue/gameplay/physic/galaxy/hyperspace_portal.py
spacerescue/gameplay/physic/galaxy/planet.py
spacerescue/gameplay/physic/galaxy/spaceship.py
spacerescue/gameplay/physic/galaxy/star.py
spacerescue/gameplay/physic/simulator/drone.py
spacerescue/gameplay/physic/simulator/drone_factory.py
spacerescue/gameplay/physic/simulator/world.py
spacerescue/gameplay/scenes/computer_console.py
spacerescue/gameplay/scenes/computer_room.py
spacerescue/gameplay/scenes/game_over.py
spacerescue/gameplay/scenes/logo_scene.py
spacerescue/gameplay/scenes/menu_scene.py
spacerescue/gameplay/scenes/quizz_console.py
spacerescue/gameplay/scenes/simulator_console.py
spacerescue/gameplay/scenes/title.py
spacerescue/gameplay/scenes/travel_in_space.py
spacerescue/gameplay/scenes/travel_to_home.py
spacerescue/gameplay/scenes/travel_to_hyperspace.py
spacerescue/gameplay/scenes/travel_to_portal.py
spacerescue/gameplay/states/game_states.py
spacerescue/gameplay/states/main_state.py
spacerescue/gameplay/widgets/blueprint_box.py
spacerescue/gameplay/widgets/monitor.py
spacerescue/mechanics/challenge.py
spacerescue/mechanics/game_board.py
spacerescue/mechanics/game_scene.py
spacerescue/mechanics/game_state.py
spacerescue-0.2.13.dist-info/LICENSE
spacerescue-0.2.13.dist-info/METADATA
spacerescue-0.2.13.dist-info/WHEEL
spacerescue-0.2.13.dist-info/RECORD
