Metadata-Version: 2.1
Name: spacerescue
Version: 0.2.13
Summary: Space Rescue - A Escape Coding Adventure
Author: Romuald Rousseau
Author-email: romuald.rousseau@servier.com
Requires-Python: >=3.11,<4.0
Classifier: Programming Language :: Python :: 3
Classifier: Programming Language :: Python :: 3.11
Classifier: Programming Language :: Python :: 3.12
Requires-Dist: coverage (>=7.4.4,<8.0.0)
Requires-Dist: duckdb (>=0.10.1,<0.11.0)
Requires-Dist: fire (>=0.6.0,<0.7.0)
Requires-Dist: numpy (>=1.26.4,<2.0.0)
Requires-Dist: numpy-quaternion (>=2023.0.3,<2024.0.0)
Requires-Dist: pandas (>=2.2.1,<3.0.0)
Requires-Dist: pyperclip (>=1.8.2,<2.0.0)
Requires-Dist: pytest (>=8.1.1,<9.0.0)
Requires-Dist: pyyaml (>=6.0.1,<7.0.0)
Requires-Dist: raylib (>=5.0.0.1,<6.0.0.0)
